<tocdiv>
<title>
第1部分 110kV及以上主变压器类设备典型缺陷
</title>
<tocdiv>
<title>
1 500kV某变电站1号主变压器B相油化验异常情况
</title>
<tocdiv>
<title>
2 500kV某变电站4号主变压器500kV侧C相套管闪络分析
</title>
<tocdiv>
<title>
3 500kV某变电站主变压器套管介损明显增长情况分析
</title>
<tocdiv>
<title>
4 220kV某变电站2号主变压器故障分析
</title>
<tocdiv>
<title>
5 110kV某变电站主变压器验收分析
</title>
<tocdiv>
<title>
6 110kV某变电站2号主变压器出厂分析
</title>
<tocdiv>
<title>
7 110kV某变电站2号主变压器本体乙炔超标分析
</title>
<tocdiv>
<title>
8 110kV某变电站2号主变压器110kV侧中性点套管绝缘不合格缺陷分析
</title>
<tocdiv>
<title>
9 110kV某变电站2号主变压器散热器严重漏油分析
</title>
<tocdiv>
<title>
10 110kV某变电站1号主变压器绕组直流电阻不平衡分析
</title>
